{
  "lastUpdate" : "2021-10-05",
  "history" : [
    {
      "statusDate" : "2020-12-22",
      "vaccinationRate" : 0.00,
      "vaccinatedPersons" : 0,
      "administeredVaccineDoses" : 2
    },
    {
      "statusDate" : "2020-12-23",
      "vaccinationRate" : 0.00,
      "vaccinatedPersons" : 0,
      "administeredVaccineDoses" : 428
    },
    {
      "statusDate" : "2020-12-24",
      "vaccinationRate" : 0.00,
      "vaccinatedPersons" : 0,
      "administeredVaccineDoses" : 692
    },
    {
      "statusDate" : "2020-12-25",
      "vaccinationRate" : 0.00,
      "vaccinatedPersons" : 0,
      "administeredVaccineDoses" : 693
    },
    {
      "statusDate" : "2020-12-26",
      "vaccinationRate" : 0.00,
      "vaccinatedPersons" : 0,
      "administeredVaccineDoses" : 1129
    },
    {
      "statusDate" : "2020-12-27",
      "vaccinationRate" : 0.00,
      "vaccinatedPersons" : 0,
      "administeredVaccineDoses" : 1129
    },
    {
      "statusDate" : "2020-12-28",
      "vaccinationRate" : 0.00,
      "vaccinatedPersons" : 2,
      "administeredVaccineDoses" : 2754
    },
    {
      "statusDate" : "2020-12-29",
      "vaccinationRate" : 0.00,
      "vaccinatedPersons" : 5,
      "administeredVaccineDoses" : 4447
    },
    {
      "statusDate" : "2020-12-30",
      "vaccinationRate" : 0.00,
      "vaccinatedPersons" : 6,
      "administeredVaccineDoses" : 6118
    },
    {
      "statusDate" : "2020-12-31",
      "vaccinationRate" : 0.00,
      "vaccinatedPersons" : 7,
      "administeredVaccineDoses" : 6371
    },
    {
      "statusDate" : "2021-01-01",
      "vaccinationRate" : 0.00,
      "vaccinatedPersons" : 8,
      "administeredVaccineDoses" : 6378
    },
    {
      "statusDate" : "2021-01-02",
      "vaccinationRate" : 0.00,
      "vaccinatedPersons" : 8,
      "administeredVaccineDoses" : 6381
    },
    {
      "statusDate" : "2021-01-03",
      "vaccinationRate" : 0.00,
      "vaccinatedPersons" : 8,
      "administeredVaccineDoses" : 6382
    },
    {
      "statusDate" : "2021-01-04",
      "vaccinationRate" : 0.00,
      "vaccinatedPersons" : 9,
      "administeredVaccineDoses" : 10047
    },
    {
      "statusDate" : "2021-01-05",
      "vaccinationRate" : 0.00,
      "vaccinatedPersons" : 10,
      "administeredVaccineDoses" : 17147
    },
    {
      "statusDate" : "2021-01-06",
      "vaccinationRate" : 0.00,
      "vaccinatedPersons" : 14,
      "administeredVaccineDoses" : 22994
    },
    {
      "statusDate" : "2021-01-07",
      "vaccinationRate" : 0.00,
      "vaccinatedPersons" : 20,
      "administeredVaccineDoses" : 30213
    },
    {
      "statusDate" : "2021-01-08",
      "vaccinationRate" : 0.00,
      "vaccinatedPersons" : 30,
      "administeredVaccineDoses" : 38252
    },
    {
      "statusDate" : "2021-01-09",
      "vaccinationRate" : 0.00,
      "vaccinatedPersons" : 33,
      "administeredVaccineDoses" : 40374
    },
    {
      "statusDate" : "2021-01-10",
      "vaccinationRate" : 0.00,
      "vaccinatedPersons" : 34,
      "administeredVaccineDoses" : 40407
    },
    {
      "statusDate" : "2021-01-11",
      "vaccinationRate" : 0.00,
      "vaccinatedPersons" : 43,
      "administeredVaccineDoses" : 47819
    },
    {
      "statusDate" : "2021-01-12",
      "vaccinationRate" : 0.00,
      "vaccinatedPersons" : 49,
      "administeredVaccineDoses" : 58221
    },
    {
      "statusDate" : "2021-01-13",
      "vaccinationRate" : 0.00,
      "vaccinatedPersons" : 176,
      "administeredVaccineDoses" : 69310
    },
    {
      "statusDate" : "2021-01-14",
      "vaccinationRate" : 0.00,
      "vaccinatedPersons" : 242,
      "administeredVaccineDoses" : 79932
    },
    {
      "statusDate" : "2021-01-15",
      "vaccinationRate" : 0.00,
      "vaccinatedPersons" : 295,
      "administeredVaccineDoses" : 90723
    },
    {
      "statusDate" : "2021-01-16",
      "vaccinationRate" : 0.00,
      "vaccinatedPersons" : 300,
      "administeredVaccineDoses" : 95083
    },
    {
      "statusDate" : "2021-01-17",
      "vaccinationRate" : 0.00,
      "vaccinatedPersons" : 304,
      "administeredVaccineDoses" : 95747
    },
    {
      "statusDate" : "2021-01-18",
      "vaccinationRate" : 0.01,
      "vaccinatedPersons" : 1056,
      "administeredVaccineDoses" : 108087
    },
    {
      "statusDate" : "2021-01-19",
      "vaccinationRate" : 0.02,
      "vaccinatedPersons" : 1758,
      "administeredVaccineDoses" : 125476
    },
    {
      "statusDate" : "2021-01-20",
      "vaccinationRate" : 0.03,
      "vaccinatedPersons" : 2669,
      "administeredVaccineDoses" : 146042
    },
    {
      "statusDate" : "2021-01-21",
      "vaccinationRate" : 0.04,
      "vaccinatedPersons" : 3240,
      "administeredVaccineDoses" : 169383
    },
    {
      "statusDate" : "2021-01-22",
      "vaccinationRate" : 0.04,
      "vaccinatedPersons" : 3728,
      "administeredVaccineDoses" : 189273
    },
    {
      "statusDate" : "2021-01-23",
      "vaccinationRate" : 0.04,
      "vaccinatedPersons" : 3824,
      "administeredVaccineDoses" : 195112
    },
    {
      "statusDate" : "2021-01-24",
      "vaccinationRate" : 0.04,
      "vaccinatedPersons" : 3836,
      "administeredVaccineDoses" : 196295
    },
    {
      "statusDate" : "2021-01-25",
      "vaccinationRate" : 0.06,
      "vaccinatedPersons" : 5285,
      "administeredVaccineDoses" : 213698
    },
    {
      "statusDate" : "2021-01-26",
      "vaccinationRate" : 0.09,
      "vaccinatedPersons" : 7842,
      "administeredVaccineDoses" : 238833
    },
    {
      "statusDate" : "2021-01-27",
      "vaccinationRate" : 0.11,
      "vaccinatedPersons" : 9821,
      "administeredVaccineDoses" : 263210
    },
    {
      "statusDate" : "2021-01-28",
      "vaccinationRate" : 0.14,
      "vaccinatedPersons" : 12525,
      "administeredVaccineDoses" : 290307
    },
    {
      "statusDate" : "2021-01-29",
      "vaccinationRate" : 0.18,
      "vaccinatedPersons" : 15161,
      "administeredVaccineDoses" : 308142
    },
    {
      "statusDate" : "2021-01-30",
      "vaccinationRate" : 0.18,
      "vaccinatedPersons" : 15161,
      "administeredVaccineDoses" : 308142
    },
    {
      "statusDate" : "2021-01-31",
      "vaccinationRate" : 0.18,
      "vaccinatedPersons" : 15161,
      "administeredVaccineDoses" : 308142
    },
    {
      "statusDate" : "2021-02-01",
      "vaccinationRate" : 0.22,
      "vaccinatedPersons" : 19375,
      "administeredVaccineDoses" : 324300
    },
    {
      "statusDate" : "2021-02-02",
      "vaccinationRate" : 0.29,
      "vaccinatedPersons" : 25087,
      "administeredVaccineDoses" : 343915
    },
    {
      "statusDate" : "2021-02-03",
      "vaccinationRate" : 0.35,
      "vaccinatedPersons" : 30421,
      "administeredVaccineDoses" : 363259
    },
    {
      "statusDate" : "2021-02-04",
      "vaccinationRate" : 0.43,
      "vaccinatedPersons" : 37480,
      "administeredVaccineDoses" : 383921
    },
    {
      "statusDate" : "2021-02-05",
      "vaccinationRate" : 0.51,
      "vaccinatedPersons" : 44497,
      "administeredVaccineDoses" : 403458
    },
    {
      "statusDate" : "2021-02-06",
      "vaccinationRate" : 0.53,
      "vaccinatedPersons" : 46026,
      "administeredVaccineDoses" : 406808
    },
    {
      "statusDate" : "2021-02-07",
      "vaccinationRate" : 0.54,
      "vaccinatedPersons" : 46299,
      "administeredVaccineDoses" : 408004
    },
    {
      "statusDate" : "2021-02-08",
      "vaccinationRate" : 0.64,
      "vaccinatedPersons" : 54900,
      "administeredVaccineDoses" : 426665
    },
    {
      "statusDate" : "2021-02-09",
      "vaccinationRate" : 0.76,
      "vaccinatedPersons" : 66013,
      "administeredVaccineDoses" : 452261
    },
    {
      "statusDate" : "2021-02-10",
      "vaccinationRate" : 0.88,
      "vaccinatedPersons" : 76230,
      "administeredVaccineDoses" : 479275
    },
    {
      "statusDate" : "2021-02-11",
      "vaccinationRate" : 1.01,
      "vaccinatedPersons" : 87513,
      "administeredVaccineDoses" : 507020
    },
    {
      "statusDate" : "2021-02-12",
      "vaccinationRate" : 1.13,
      "vaccinatedPersons" : 97699,
      "administeredVaccineDoses" : 533598
    },
    {
      "statusDate" : "2021-02-13",
      "vaccinationRate" : 1.17,
      "vaccinatedPersons" : 101245,
      "administeredVaccineDoses" : 540546
    },
    {
      "statusDate" : "2021-02-14",
      "vaccinationRate" : 1.18,
      "vaccinatedPersons" : 101749,
      "administeredVaccineDoses" : 541892
    },
    {
      "statusDate" : "2021-02-15",
      "vaccinationRate" : 1.28,
      "vaccinatedPersons" : 110774,
      "administeredVaccineDoses" : 560885
    },
    {
      "statusDate" : "2021-02-16",
      "vaccinationRate" : 1.42,
      "vaccinatedPersons" : 123111,
      "administeredVaccineDoses" : 586175
    },
    {
      "statusDate" : "2021-02-17",
      "vaccinationRate" : 1.58,
      "vaccinatedPersons" : 136666,
      "administeredVaccineDoses" : 610625
    },
    {
      "statusDate" : "2021-02-18",
      "vaccinationRate" : 1.77,
      "vaccinatedPersons" : 153306,
      "administeredVaccineDoses" : 639389
    },
    {
      "statusDate" : "2021-02-19",
      "vaccinationRate" : 1.94,
      "vaccinatedPersons" : 167942,
      "administeredVaccineDoses" : 663895
    },
    {
      "statusDate" : "2021-02-20",
      "vaccinationRate" : 2.00,
      "vaccinatedPersons" : 172477,
      "administeredVaccineDoses" : 671161
    },
    {
      "statusDate" : "2021-02-21",
      "vaccinationRate" : 2.00,
      "vaccinatedPersons" : 173317,
      "administeredVaccineDoses" : 672809
    },
    {
      "statusDate" : "2021-02-22",
      "vaccinationRate" : 2.15,
      "vaccinatedPersons" : 186162,
      "administeredVaccineDoses" : 692945
    },
    {
      "statusDate" : "2021-02-23",
      "vaccinationRate" : 2.35,
      "vaccinatedPersons" : 202795,
      "administeredVaccineDoses" : 719809
    },
    {
      "statusDate" : "2021-02-24",
      "vaccinationRate" : 2.56,
      "vaccinatedPersons" : 220898,
      "administeredVaccineDoses" : 748103
    },
    {
      "statusDate" : "2021-02-25",
      "vaccinationRate" : 2.78,
      "vaccinatedPersons" : 240272,
      "administeredVaccineDoses" : 777824
    },
    {
      "statusDate" : "2021-02-26",
      "vaccinationRate" : 2.97,
      "vaccinatedPersons" : 256604,
      "administeredVaccineDoses" : 802753
    },
    {
      "statusDate" : "2021-02-27",
      "vaccinationRate" : 3.02,
      "vaccinatedPersons" : 260975,
      "administeredVaccineDoses" : 809317
    },
    {
      "statusDate" : "2021-02-28",
      "vaccinationRate" : 3.03,
      "vaccinatedPersons" : 262351,
      "administeredVaccineDoses" : 811306
    },
    {
      "statusDate" : "2021-03-01",
      "vaccinationRate" : 3.17,
      "vaccinatedPersons" : 273973,
      "administeredVaccineDoses" : 833575
    },
    {
      "statusDate" : "2021-03-02",
      "vaccinationRate" : 3.33,
      "vaccinatedPersons" : 288254,
      "administeredVaccineDoses" : 859562
    },
    {
      "statusDate" : "2021-03-03",
      "vaccinationRate" : 3.52,
      "vaccinatedPersons" : 304229,
      "administeredVaccineDoses" : 891575
    },
    {
      "statusDate" : "2021-03-04",
      "vaccinationRate" : 3.70,
      "vaccinatedPersons" : 320206,
      "administeredVaccineDoses" : 925385
    },
    {
      "statusDate" : "2021-03-05",
      "vaccinationRate" : 3.87,
      "vaccinatedPersons" : 334485,
      "administeredVaccineDoses" : 954821
    },
    {
      "statusDate" : "2021-03-06",
      "vaccinationRate" : 3.90,
      "vaccinatedPersons" : 337336,
      "administeredVaccineDoses" : 961145
    },
    {
      "statusDate" : "2021-03-07",
      "vaccinationRate" : 3.91,
      "vaccinatedPersons" : 338265,
      "administeredVaccineDoses" : 963101
    },
    {
      "statusDate" : "2021-03-08",
      "vaccinationRate" : 4.03,
      "vaccinatedPersons" : 348576,
      "administeredVaccineDoses" : 986558
    },
    {
      "statusDate" : "2021-03-09",
      "vaccinationRate" : 4.18,
      "vaccinatedPersons" : 361521,
      "administeredVaccineDoses" : 1017253
    },
    {
      "statusDate" : "2021-03-10",
      "vaccinationRate" : 4.31,
      "vaccinatedPersons" : 372691,
      "administeredVaccineDoses" : 1047692
    },
    {
      "statusDate" : "2021-03-11",
      "vaccinationRate" : 4.46,
      "vaccinatedPersons" : 385580,
      "administeredVaccineDoses" : 1080164
    },
    {
      "statusDate" : "2021-03-12",
      "vaccinationRate" : 4.59,
      "vaccinatedPersons" : 397006,
      "administeredVaccineDoses" : 1107722
    },
    {
      "statusDate" : "2021-03-13",
      "vaccinationRate" : 4.62,
      "vaccinatedPersons" : 399248,
      "administeredVaccineDoses" : 1113746
    },
    {
      "statusDate" : "2021-03-14",
      "vaccinationRate" : 4.62,
      "vaccinatedPersons" : 399709,
      "administeredVaccineDoses" : 1115194
    },
    {
      "statusDate" : "2021-03-15",
      "vaccinationRate" : 4.74,
      "vaccinatedPersons" : 409875,
      "administeredVaccineDoses" : 1136301
    },
    {
      "statusDate" : "2021-03-16",
      "vaccinationRate" : 4.90,
      "vaccinatedPersons" : 423749,
      "administeredVaccineDoses" : 1165425
    },
    {
      "statusDate" : "2021-03-17",
      "vaccinationRate" : 5.09,
      "vaccinatedPersons" : 439787,
      "administeredVaccineDoses" : 1197364
    },
    {
      "statusDate" : "2021-03-18",
      "vaccinationRate" : 5.28,
      "vaccinatedPersons" : 456093,
      "administeredVaccineDoses" : 1230947
    },
    {
      "statusDate" : "2021-03-19",
      "vaccinationRate" : 5.43,
      "vaccinatedPersons" : 469132,
      "administeredVaccineDoses" : 1258941
    },
    {
      "statusDate" : "2021-03-20",
      "vaccinationRate" : 5.46,
      "vaccinatedPersons" : 471952,
      "administeredVaccineDoses" : 1265145
    },
    {
      "statusDate" : "2021-03-21",
      "vaccinationRate" : 5.46,
      "vaccinatedPersons" : 472343,
      "administeredVaccineDoses" : 1266495
    },
    {
      "statusDate" : "2021-03-22",
      "vaccinationRate" : 5.59,
      "vaccinatedPersons" : 483598,
      "administeredVaccineDoses" : 1291546
    },
    {
      "statusDate" : "2021-03-23",
      "vaccinationRate" : 5.76,
      "vaccinatedPersons" : 497577,
      "administeredVaccineDoses" : 1324209
    },
    {
      "statusDate" : "2021-03-24",
      "vaccinationRate" : 5.92,
      "vaccinatedPersons" : 511376,
      "administeredVaccineDoses" : 1359657
    },
    {
      "statusDate" : "2021-03-25",
      "vaccinationRate" : 6.07,
      "vaccinatedPersons" : 524869,
      "administeredVaccineDoses" : 1398856
    },
    {
      "statusDate" : "2021-03-26",
      "vaccinationRate" : 6.22,
      "vaccinatedPersons" : 537384,
      "administeredVaccineDoses" : 1435235
    },
    {
      "statusDate" : "2021-03-27",
      "vaccinationRate" : 6.25,
      "vaccinatedPersons" : 539930,
      "administeredVaccineDoses" : 1445387
    },
    {
      "statusDate" : "2021-03-28",
      "vaccinationRate" : 6.25,
      "vaccinatedPersons" : 540638,
      "administeredVaccineDoses" : 1449000
    },
    {
      "statusDate" : "2021-03-29",
      "vaccinationRate" : 6.39,
      "vaccinatedPersons" : 552725,
      "administeredVaccineDoses" : 1482517
    },
    {
      "statusDate" : "2021-03-30",
      "vaccinationRate" : 6.55,
      "vaccinatedPersons" : 565935,
      "administeredVaccineDoses" : 1524321
    },
    {
      "statusDate" : "2021-03-31",
      "vaccinationRate" : 6.72,
      "vaccinatedPersons" : 580669,
      "administeredVaccineDoses" : 1563353
    },
    {
      "statusDate" : "2021-04-01",
      "vaccinationRate" : 6.92,
      "vaccinatedPersons" : 598419,
      "administeredVaccineDoses" : 1605258
    },
    {
      "statusDate" : "2021-04-02",
      "vaccinationRate" : 6.97,
      "vaccinatedPersons" : 602953,
      "administeredVaccineDoses" : 1615898
    },
    {
      "statusDate" : "2021-04-03",
      "vaccinationRate" : 7.00,
      "vaccinatedPersons" : 605472,
      "administeredVaccineDoses" : 1622359
    },
    {
      "statusDate" : "2021-04-04",
      "vaccinationRate" : 7.01,
      "vaccinatedPersons" : 606146,
      "administeredVaccineDoses" : 1624094
    },
    {
      "statusDate" : "2021-04-05",
      "vaccinationRate" : 7.04,
      "vaccinatedPersons" : 608317,
      "administeredVaccineDoses" : 1629987
    },
    {
      "statusDate" : "2021-04-06",
      "vaccinationRate" : 7.26,
      "vaccinatedPersons" : 627780,
      "administeredVaccineDoses" : 1668559
    },
    {
      "statusDate" : "2021-04-07",
      "vaccinationRate" : 7.50,
      "vaccinatedPersons" : 648019,
      "administeredVaccineDoses" : 1715327
    },
    {
      "statusDate" : "2021-04-08",
      "vaccinationRate" : 7.75,
      "vaccinatedPersons" : 669638,
      "administeredVaccineDoses" : 1767874
    },
    {
      "statusDate" : "2021-04-09",
      "vaccinationRate" : 7.95,
      "vaccinatedPersons" : 687288,
      "administeredVaccineDoses" : 1815972
    },
    {
      "statusDate" : "2021-04-10",
      "vaccinationRate" : 8.00,
      "vaccinatedPersons" : 691503,
      "administeredVaccineDoses" : 1830631
    },
    {
      "statusDate" : "2021-04-11",
      "vaccinationRate" : 8.01,
      "vaccinatedPersons" : 692802,
      "administeredVaccineDoses" : 1834757
    },
    {
      "statusDate" : "2021-04-12",
      "vaccinationRate" : 8.16,
      "vaccinatedPersons" : 705743,
      "administeredVaccineDoses" : 1879578
    },
    {
      "statusDate" : "2021-04-13",
      "vaccinationRate" : 8.36,
      "vaccinatedPersons" : 722390,
      "administeredVaccineDoses" : 1934131
    },
    {
      "statusDate" : "2021-04-14",
      "vaccinationRate" : 8.55,
      "vaccinatedPersons" : 739295,
      "administeredVaccineDoses" : 1991596
    },
    {
      "statusDate" : "2021-04-15",
      "vaccinationRate" : 8.75,
      "vaccinatedPersons" : 756381,
      "administeredVaccineDoses" : 2050433
    },
    {
      "statusDate" : "2021-04-16",
      "vaccinationRate" : 8.94,
      "vaccinatedPersons" : 772554,
      "administeredVaccineDoses" : 2105699
    },
    {
      "statusDate" : "2021-04-17",
      "vaccinationRate" : 8.98,
      "vaccinatedPersons" : 776298,
      "administeredVaccineDoses" : 2123750
    },
    {
      "statusDate" : "2021-04-18",
      "vaccinationRate" : 8.99,
      "vaccinatedPersons" : 777222,
      "administeredVaccineDoses" : 2130137
    },
    {
      "statusDate" : "2021-04-19",
      "vaccinationRate" : 9.17,
      "vaccinatedPersons" : 792350,
      "administeredVaccineDoses" : 2182526
    },
    {
      "statusDate" : "2021-04-20",
      "vaccinationRate" : 9.39,
      "vaccinatedPersons" : 812122,
      "administeredVaccineDoses" : 2247337
    },
    {
      "statusDate" : "2021-04-21",
      "vaccinationRate" : 9.63,
      "vaccinatedPersons" : 832866,
      "administeredVaccineDoses" : 2315640
    },
    {
      "statusDate" : "2021-04-22",
      "vaccinationRate" : 9.91,
      "vaccinatedPersons" : 856861,
      "administeredVaccineDoses" : 2391107
    },
    {
      "statusDate" : "2021-04-23",
      "vaccinationRate" : 10.15,
      "vaccinatedPersons" : 877405,
      "administeredVaccineDoses" : 2458267
    },
    {
      "statusDate" : "2021-04-24",
      "vaccinationRate" : 10.22,
      "vaccinatedPersons" : 883778,
      "administeredVaccineDoses" : 2485710
    },
    {
      "statusDate" : "2021-04-25",
      "vaccinationRate" : 10.25,
      "vaccinatedPersons" : 886467,
      "administeredVaccineDoses" : 2497797
    },
    {
      "statusDate" : "2021-04-26",
      "vaccinationRate" : 10.48,
      "vaccinatedPersons" : 905885,
      "administeredVaccineDoses" : 2555286
    },
    {
      "statusDate" : "2021-04-27",
      "vaccinationRate" : 10.77,
      "vaccinatedPersons" : 930790,
      "administeredVaccineDoses" : 2630335
    },
    {
      "statusDate" : "2021-04-28",
      "vaccinationRate" : 11.02,
      "vaccinatedPersons" : 952548,
      "administeredVaccineDoses" : 2704600
    },
    {
      "statusDate" : "2021-04-29",
      "vaccinationRate" : 11.29,
      "vaccinatedPersons" : 975811,
      "administeredVaccineDoses" : 2778209
    },
    {
      "statusDate" : "2021-04-30",
      "vaccinationRate" : 11.43,
      "vaccinatedPersons" : 988381,
      "administeredVaccineDoses" : 2843441
    },
    {
      "statusDate" : "2021-05-01",
      "vaccinationRate" : 11.48,
      "vaccinatedPersons" : 992311,
      "administeredVaccineDoses" : 2873594
    },
    {
      "statusDate" : "2021-05-02",
      "vaccinationRate" : 11.49,
      "vaccinatedPersons" : 993315,
      "administeredVaccineDoses" : 2886231
    },
    {
      "statusDate" : "2021-05-03",
      "vaccinationRate" : 11.61,
      "vaccinatedPersons" : 1003640,
      "administeredVaccineDoses" : 2947460
    },
    {
      "statusDate" : "2021-05-04",
      "vaccinationRate" : 11.86,
      "vaccinatedPersons" : 1025231,
      "administeredVaccineDoses" : 3024090
    },
    {
      "statusDate" : "2021-05-05",
      "vaccinationRate" : 12.17,
      "vaccinatedPersons" : 1051902,
      "administeredVaccineDoses" : 3103468
    },
    {
      "statusDate" : "2021-05-06",
      "vaccinationRate" : 12.53,
      "vaccinatedPersons" : 1083534,
      "administeredVaccineDoses" : 3194684
    },
    {
      "statusDate" : "2021-05-07",
      "vaccinationRate" : 12.89,
      "vaccinatedPersons" : 1114407,
      "administeredVaccineDoses" : 3281146
    },
    {
      "statusDate" : "2021-05-08",
      "vaccinationRate" : 13.01,
      "vaccinatedPersons" : 1125063,
      "administeredVaccineDoses" : 3321787
    },
    {
      "statusDate" : "2021-05-09",
      "vaccinationRate" : 13.05,
      "vaccinatedPersons" : 1128441,
      "administeredVaccineDoses" : 3337886
    },
    {
      "statusDate" : "2021-05-10",
      "vaccinationRate" : 13.45,
      "vaccinatedPersons" : 1162811,
      "administeredVaccineDoses" : 3419747
    },
    {
      "statusDate" : "2021-05-11",
      "vaccinationRate" : 13.92,
      "vaccinatedPersons" : 1203778,
      "administeredVaccineDoses" : 3516660
    },
    {
      "statusDate" : "2021-05-12",
      "vaccinationRate" : 14.43,
      "vaccinatedPersons" : 1247068,
      "administeredVaccineDoses" : 3615143
    },
    {
      "statusDate" : "2021-05-13",
      "vaccinationRate" : 14.61,
      "vaccinatedPersons" : 1263069,
      "administeredVaccineDoses" : 3661452
    },
    {
      "statusDate" : "2021-05-14",
      "vaccinationRate" : 15.04,
      "vaccinatedPersons" : 1300034,
      "administeredVaccineDoses" : 3743734
    },
    {
      "statusDate" : "2021-05-15",
      "vaccinationRate" : 15.19,
      "vaccinatedPersons" : 1313241,
      "administeredVaccineDoses" : 3787923
    },
    {
      "statusDate" : "2021-05-16",
      "vaccinationRate" : 15.24,
      "vaccinatedPersons" : 1317618,
      "administeredVaccineDoses" : 3806945
    },
    {
      "statusDate" : "2021-05-17",
      "vaccinationRate" : 15.73,
      "vaccinatedPersons" : 1359942,
      "administeredVaccineDoses" : 3892333
    },
    {
      "statusDate" : "2021-05-18",
      "vaccinationRate" : 16.30,
      "vaccinatedPersons" : 1408829,
      "administeredVaccineDoses" : 3993844
    },
    {
      "statusDate" : "2021-05-19",
      "vaccinationRate" : 16.84,
      "vaccinatedPersons" : 1456034,
      "administeredVaccineDoses" : 4097368
    },
    {
      "statusDate" : "2021-05-20",
      "vaccinationRate" : 17.45,
      "vaccinatedPersons" : 1508684,
      "administeredVaccineDoses" : 4208147
    },
    {
      "statusDate" : "2021-05-21",
      "vaccinationRate" : 17.99,
      "vaccinatedPersons" : 1555417,
      "administeredVaccineDoses" : 4311255
    },
    {
      "statusDate" : "2021-05-22",
      "vaccinationRate" : 18.19,
      "vaccinatedPersons" : 1572434,
      "administeredVaccineDoses" : 4358969
    },
    {
      "statusDate" : "2021-05-23",
      "vaccinationRate" : 18.26,
      "vaccinatedPersons" : 1578540,
      "administeredVaccineDoses" : 4377701
    },
    {
      "statusDate" : "2021-05-24",
      "vaccinationRate" : 18.49,
      "vaccinatedPersons" : 1598192,
      "administeredVaccineDoses" : 4428294
    },
    {
      "statusDate" : "2021-05-25",
      "vaccinationRate" : 19.10,
      "vaccinatedPersons" : 1650962,
      "administeredVaccineDoses" : 4531028
    },
    {
      "statusDate" : "2021-05-26",
      "vaccinationRate" : 19.72,
      "vaccinatedPersons" : 1704930,
      "administeredVaccineDoses" : 4639234
    },
    {
      "statusDate" : "2021-05-27",
      "vaccinationRate" : 20.33,
      "vaccinatedPersons" : 1757637,
      "administeredVaccineDoses" : 4748597
    },
    {
      "statusDate" : "2021-05-28",
      "vaccinationRate" : 20.96,
      "vaccinatedPersons" : 1812377,
      "administeredVaccineDoses" : 4854998
    },
    {
      "statusDate" : "2021-05-29",
      "vaccinationRate" : 21.27,
      "vaccinatedPersons" : 1838807,
      "administeredVaccineDoses" : 4909578
    },
    {
      "statusDate" : "2021-05-30",
      "vaccinationRate" : 21.40,
      "vaccinatedPersons" : 1849784,
      "administeredVaccineDoses" : 4934237
    },
    {
      "statusDate" : "2021-05-31",
      "vaccinationRate" : 21.98,
      "vaccinatedPersons" : 1899722,
      "administeredVaccineDoses" : 5028591
    },
    {
      "statusDate" : "2021-06-01",
      "vaccinationRate" : 22.61,
      "vaccinatedPersons" : 1954574,
      "administeredVaccineDoses" : 5138186
    },
    {
      "statusDate" : "2021-06-02",
      "vaccinationRate" : 23.25,
      "vaccinatedPersons" : 2009879,
      "administeredVaccineDoses" : 5251811
    },
    {
      "statusDate" : "2021-06-03",
      "vaccinationRate" : 23.83,
      "vaccinatedPersons" : 2059705,
      "administeredVaccineDoses" : 5356277
    },
    {
      "statusDate" : "2021-06-04",
      "vaccinationRate" : 24.48,
      "vaccinatedPersons" : 2116136,
      "administeredVaccineDoses" : 5468448
    },
    {
      "statusDate" : "2021-06-05",
      "vaccinationRate" : 24.83,
      "vaccinatedPersons" : 2146505,
      "administeredVaccineDoses" : 5542193
    },
    {
      "statusDate" : "2021-06-06",
      "vaccinationRate" : 24.97,
      "vaccinatedPersons" : 2158732,
      "administeredVaccineDoses" : 5569904
    },
    {
      "statusDate" : "2021-06-07",
      "vaccinationRate" : 25.55,
      "vaccinatedPersons" : 2209101,
      "administeredVaccineDoses" : 5672759
    },
    {
      "statusDate" : "2021-06-08",
      "vaccinationRate" : 26.22,
      "vaccinatedPersons" : 2266620,
      "administeredVaccineDoses" : 5785926
    },
    {
      "statusDate" : "2021-06-09",
      "vaccinationRate" : 26.86,
      "vaccinatedPersons" : 2321644,
      "administeredVaccineDoses" : 5899796
    },
    {
      "statusDate" : "2021-06-10",
      "vaccinationRate" : 27.37,
      "vaccinatedPersons" : 2366418,
      "administeredVaccineDoses" : 6006525
    },
    {
      "statusDate" : "2021-06-11",
      "vaccinationRate" : 27.95,
      "vaccinatedPersons" : 2416071,
      "administeredVaccineDoses" : 6115885
    },
    {
      "statusDate" : "2021-06-12",
      "vaccinationRate" : 28.30,
      "vaccinatedPersons" : 2446437,
      "administeredVaccineDoses" : 6187163
    },
    {
      "statusDate" : "2021-06-13",
      "vaccinationRate" : 28.48,
      "vaccinatedPersons" : 2461710,
      "administeredVaccineDoses" : 6213964
    },
    {
      "statusDate" : "2021-06-14",
      "vaccinationRate" : 29.00,
      "vaccinatedPersons" : 2507071,
      "administeredVaccineDoses" : 6312821
    },
    {
      "statusDate" : "2021-06-15",
      "vaccinationRate" : 29.62,
      "vaccinatedPersons" : 2560164,
      "administeredVaccineDoses" : 6418107
    },
    {
      "statusDate" : "2021-06-16",
      "vaccinationRate" : 30.25,
      "vaccinatedPersons" : 2615080,
      "administeredVaccineDoses" : 6522412
    },
    {
      "statusDate" : "2021-06-17",
      "vaccinationRate" : 30.92,
      "vaccinatedPersons" : 2673329,
      "administeredVaccineDoses" : 6629917
    },
    {
      "statusDate" : "2021-06-18",
      "vaccinationRate" : 31.59,
      "vaccinatedPersons" : 2731059,
      "administeredVaccineDoses" : 6733470
    },
    {
      "statusDate" : "2021-06-19",
      "vaccinationRate" : 31.94,
      "vaccinatedPersons" : 2761470,
      "administeredVaccineDoses" : 6796745
    },
    {
      "statusDate" : "2021-06-20",
      "vaccinationRate" : 32.08,
      "vaccinatedPersons" : 2773520,
      "administeredVaccineDoses" : 6817571
    },
    {
      "statusDate" : "2021-06-21",
      "vaccinationRate" : 32.61,
      "vaccinatedPersons" : 2818700,
      "administeredVaccineDoses" : 6905888
    },
    {
      "statusDate" : "2021-06-22",
      "vaccinationRate" : 33.23,
      "vaccinatedPersons" : 2872414,
      "administeredVaccineDoses" : 6998977
    },
    {
      "statusDate" : "2021-06-23",
      "vaccinationRate" : 33.85,
      "vaccinatedPersons" : 2926603,
      "administeredVaccineDoses" : 7089448
    },
    {
      "statusDate" : "2021-06-24",
      "vaccinationRate" : 34.50,
      "vaccinatedPersons" : 2982715,
      "administeredVaccineDoses" : 7178717
    },
    {
      "statusDate" : "2021-06-25",
      "vaccinationRate" : 35.13,
      "vaccinatedPersons" : 3036760,
      "administeredVaccineDoses" : 7266880
    },
    {
      "statusDate" : "2021-06-26",
      "vaccinationRate" : 35.46,
      "vaccinatedPersons" : 3065181,
      "administeredVaccineDoses" : 7318156
    },
    {
      "statusDate" : "2021-06-27",
      "vaccinationRate" : 35.62,
      "vaccinatedPersons" : 3079017,
      "administeredVaccineDoses" : 7336684
    },
    {
      "statusDate" : "2021-06-28",
      "vaccinationRate" : 36.21,
      "vaccinatedPersons" : 3130129,
      "administeredVaccineDoses" : 7411890
    },
    {
      "statusDate" : "2021-06-29",
      "vaccinationRate" : 36.86,
      "vaccinatedPersons" : 3186689,
      "administeredVaccineDoses" : 7491649
    },
    {
      "statusDate" : "2021-06-30",
      "vaccinationRate" : 37.58,
      "vaccinatedPersons" : 3248759,
      "administeredVaccineDoses" : 7575350
    },
    {
      "statusDate" : "2021-07-01",
      "vaccinationRate" : 38.21,
      "vaccinatedPersons" : 3303529,
      "administeredVaccineDoses" : 7648846
    },
    {
      "statusDate" : "2021-07-02",
      "vaccinationRate" : 38.87,
      "vaccinatedPersons" : 3359926,
      "administeredVaccineDoses" : 7723745
    },
    {
      "statusDate" : "2021-07-03",
      "vaccinationRate" : 39.31,
      "vaccinatedPersons" : 3397965,
      "administeredVaccineDoses" : 7771238
    },
    {
      "statusDate" : "2021-07-04",
      "vaccinationRate" : 39.45,
      "vaccinatedPersons" : 3410410,
      "administeredVaccineDoses" : 7786182
    },
    {
      "statusDate" : "2021-07-05",
      "vaccinationRate" : 40.11,
      "vaccinatedPersons" : 3467673,
      "administeredVaccineDoses" : 7858164
    },
    {
      "statusDate" : "2021-07-06",
      "vaccinationRate" : 40.77,
      "vaccinatedPersons" : 3524161,
      "administeredVaccineDoses" : 7932057
    },
    {
      "statusDate" : "2021-07-07",
      "vaccinationRate" : 41.41,
      "vaccinatedPersons" : 3580027,
      "administeredVaccineDoses" : 8003238
    },
    {
      "statusDate" : "2021-07-08",
      "vaccinationRate" : 42.10,
      "vaccinatedPersons" : 3639209,
      "administeredVaccineDoses" : 8075518
    },
    {
      "statusDate" : "2021-07-09",
      "vaccinationRate" : 42.77,
      "vaccinatedPersons" : 3697187,
      "administeredVaccineDoses" : 8146911
    },
    {
      "statusDate" : "2021-07-10",
      "vaccinationRate" : 43.18,
      "vaccinatedPersons" : 3733153,
      "administeredVaccineDoses" : 8189069
    },
    {
      "statusDate" : "2021-07-11",
      "vaccinationRate" : 43.30,
      "vaccinatedPersons" : 3743529,
      "administeredVaccineDoses" : 8200772
    },
    {
      "statusDate" : "2021-07-12",
      "vaccinationRate" : 43.97,
      "vaccinatedPersons" : 3801294,
      "administeredVaccineDoses" : 8270984
    },
    {
      "statusDate" : "2021-07-13",
      "vaccinationRate" : 44.62,
      "vaccinatedPersons" : 3857499,
      "administeredVaccineDoses" : 8340557
    },
    {
      "statusDate" : "2021-07-14",
      "vaccinationRate" : 45.19,
      "vaccinatedPersons" : 3906721,
      "administeredVaccineDoses" : 8402959
    },
    {
      "statusDate" : "2021-07-15",
      "vaccinationRate" : 45.75,
      "vaccinatedPersons" : 3955299,
      "administeredVaccineDoses" : 8464701
    },
    {
      "statusDate" : "2021-07-16",
      "vaccinationRate" : 46.30,
      "vaccinatedPersons" : 4002882,
      "administeredVaccineDoses" : 8525761
    },
    {
      "statusDate" : "2021-07-17",
      "vaccinationRate" : 46.62,
      "vaccinatedPersons" : 4030273,
      "administeredVaccineDoses" : 8558973
    },
    {
      "statusDate" : "2021-07-18",
      "vaccinationRate" : 46.70,
      "vaccinatedPersons" : 4037326,
      "administeredVaccineDoses" : 8566838
    },
    {
      "statusDate" : "2021-07-19",
      "vaccinationRate" : 47.31,
      "vaccinatedPersons" : 4089455,
      "administeredVaccineDoses" : 8630971
    },
    {
      "statusDate" : "2021-07-20",
      "vaccinationRate" : 47.80,
      "vaccinatedPersons" : 4132529,
      "administeredVaccineDoses" : 8686704
    },
    {
      "statusDate" : "2021-07-21",
      "vaccinationRate" : 48.23,
      "vaccinatedPersons" : 4169238,
      "administeredVaccineDoses" : 8736438
    },
    {
      "statusDate" : "2021-07-22",
      "vaccinationRate" : 48.62,
      "vaccinatedPersons" : 4203358,
      "administeredVaccineDoses" : 8781841
    },
    {
      "statusDate" : "2021-07-23",
      "vaccinationRate" : 49.04,
      "vaccinatedPersons" : 4239248,
      "administeredVaccineDoses" : 8830847
    },
    {
      "statusDate" : "2021-07-24",
      "vaccinationRate" : 49.27,
      "vaccinatedPersons" : 4259520,
      "administeredVaccineDoses" : 8856493
    },
    {
      "statusDate" : "2021-07-25",
      "vaccinationRate" : 49.32,
      "vaccinatedPersons" : 4263577,
      "administeredVaccineDoses" : 8861388
    },
    {
      "statusDate" : "2021-07-26",
      "vaccinationRate" : 49.67,
      "vaccinatedPersons" : 4293802,
      "administeredVaccineDoses" : 8904450
    },
    {
      "statusDate" : "2021-07-27",
      "vaccinationRate" : 49.95,
      "vaccinatedPersons" : 4318473,
      "administeredVaccineDoses" : 8940284
    },
    {
      "statusDate" : "2021-07-28",
      "vaccinationRate" : 50.19,
      "vaccinatedPersons" : 4339025,
      "administeredVaccineDoses" : 8972220
    },
    {
      "statusDate" : "2021-07-29",
      "vaccinationRate" : 50.43,
      "vaccinatedPersons" : 4359341,
      "administeredVaccineDoses" : 9003254
    },
    {
      "statusDate" : "2021-07-30",
      "vaccinationRate" : 50.66,
      "vaccinatedPersons" : 4379515,
      "administeredVaccineDoses" : 9035464
    },
    {
      "statusDate" : "2021-07-31",
      "vaccinationRate" : 50.74,
      "vaccinatedPersons" : 4386716,
      "administeredVaccineDoses" : 9046893
    },
    {
      "statusDate" : "2021-08-01",
      "vaccinationRate" : 50.76,
      "vaccinatedPersons" : 4387854,
      "administeredVaccineDoses" : 9048368
    },
    {
      "statusDate" : "2021-08-02",
      "vaccinationRate" : 50.92,
      "vaccinatedPersons" : 4402285,
      "administeredVaccineDoses" : 9070266
    },
    {
      "statusDate" : "2021-08-03",
      "vaccinationRate" : 51.13,
      "vaccinatedPersons" : 4420270,
      "administeredVaccineDoses" : 9097078
    },
    {
      "statusDate" : "2021-08-04",
      "vaccinationRate" : 51.30,
      "vaccinatedPersons" : 4434548,
      "administeredVaccineDoses" : 9121222
    },
    {
      "statusDate" : "2021-08-05",
      "vaccinationRate" : 51.48,
      "vaccinatedPersons" : 4450255,
      "administeredVaccineDoses" : 9146591
    },
    {
      "statusDate" : "2021-08-06",
      "vaccinationRate" : 51.68,
      "vaccinatedPersons" : 4467502,
      "administeredVaccineDoses" : 9174779
    },
    {
      "statusDate" : "2021-08-07",
      "vaccinationRate" : 51.74,
      "vaccinatedPersons" : 4472813,
      "administeredVaccineDoses" : 9184019
    },
    {
      "statusDate" : "2021-08-08",
      "vaccinationRate" : 51.75,
      "vaccinatedPersons" : 4473439,
      "administeredVaccineDoses" : 9184844
    },
    {
      "statusDate" : "2021-08-09",
      "vaccinationRate" : 51.91,
      "vaccinatedPersons" : 4487208,
      "administeredVaccineDoses" : 9207389
    },
    {
      "statusDate" : "2021-08-10",
      "vaccinationRate" : 52.06,
      "vaccinatedPersons" : 4500554,
      "administeredVaccineDoses" : 9230219
    },
    {
      "statusDate" : "2021-08-11",
      "vaccinationRate" : 52.22,
      "vaccinatedPersons" : 4514602,
      "administeredVaccineDoses" : 9254447
    },
    {
      "statusDate" : "2021-08-12",
      "vaccinationRate" : 52.39,
      "vaccinatedPersons" : 4529023,
      "administeredVaccineDoses" : 9280696
    },
    {
      "statusDate" : "2021-08-13",
      "vaccinationRate" : 52.57,
      "vaccinatedPersons" : 4544345,
      "administeredVaccineDoses" : 9308768
    },
    {
      "statusDate" : "2021-08-14",
      "vaccinationRate" : 52.62,
      "vaccinatedPersons" : 4549312,
      "administeredVaccineDoses" : 9319246
    },
    {
      "statusDate" : "2021-08-15",
      "vaccinationRate" : 52.63,
      "vaccinatedPersons" : 4549614,
      "administeredVaccineDoses" : 9319827
    },
    {
      "statusDate" : "2021-08-16",
      "vaccinationRate" : 52.78,
      "vaccinatedPersons" : 4562573,
      "administeredVaccineDoses" : 9341789
    },
    {
      "statusDate" : "2021-08-17",
      "vaccinationRate" : 52.93,
      "vaccinatedPersons" : 4575724,
      "administeredVaccineDoses" : 9365629
    },
    {
      "statusDate" : "2021-08-18",
      "vaccinationRate" : 53.10,
      "vaccinatedPersons" : 4590272,
      "administeredVaccineDoses" : 9392583
    },
    {
      "statusDate" : "2021-08-19",
      "vaccinationRate" : 53.25,
      "vaccinatedPersons" : 4603046,
      "administeredVaccineDoses" : 9418551
    },
    {
      "statusDate" : "2021-08-20",
      "vaccinationRate" : 53.44,
      "vaccinatedPersons" : 4619453,
      "administeredVaccineDoses" : 9450550
    },
    {
      "statusDate" : "2021-08-21",
      "vaccinationRate" : 53.50,
      "vaccinatedPersons" : 4624676,
      "administeredVaccineDoses" : 9462989
    },
    {
      "statusDate" : "2021-08-22",
      "vaccinationRate" : 53.50,
      "vaccinatedPersons" : 4625123,
      "administeredVaccineDoses" : 9463867
    },
    {
      "statusDate" : "2021-08-23",
      "vaccinationRate" : 53.64,
      "vaccinatedPersons" : 4636741,
      "administeredVaccineDoses" : 9486536
    },
    {
      "statusDate" : "2021-08-24",
      "vaccinationRate" : 53.78,
      "vaccinatedPersons" : 4649032,
      "administeredVaccineDoses" : 9511379
    },
    {
      "statusDate" : "2021-08-25",
      "vaccinationRate" : 53.94,
      "vaccinatedPersons" : 4662926,
      "administeredVaccineDoses" : 9540343
    },
    {
      "statusDate" : "2021-08-26",
      "vaccinationRate" : 54.09,
      "vaccinatedPersons" : 4676153,
      "administeredVaccineDoses" : 9569762
    },
    {
      "statusDate" : "2021-08-27",
      "vaccinationRate" : 54.27,
      "vaccinatedPersons" : 4691850,
      "administeredVaccineDoses" : 9604622
    },
    {
      "statusDate" : "2021-08-28",
      "vaccinationRate" : 54.35,
      "vaccinatedPersons" : 4698281,
      "administeredVaccineDoses" : 9622002
    },
    {
      "statusDate" : "2021-08-29",
      "vaccinationRate" : 54.35,
      "vaccinatedPersons" : 4698792,
      "administeredVaccineDoses" : 9623924
    },
    {
      "statusDate" : "2021-08-30",
      "vaccinationRate" : 54.46,
      "vaccinatedPersons" : 4707820,
      "administeredVaccineDoses" : 9646757
    },
    {
      "statusDate" : "2021-08-31",
      "vaccinationRate" : 54.57,
      "vaccinatedPersons" : 4717596,
      "administeredVaccineDoses" : 9670844
    },
    {
      "statusDate" : "2021-09-01",
      "vaccinationRate" : 54.71,
      "vaccinatedPersons" : 4729455,
      "administeredVaccineDoses" : 9698917
    },
    {
      "statusDate" : "2021-09-02",
      "vaccinationRate" : 54.84,
      "vaccinatedPersons" : 4740457,
      "administeredVaccineDoses" : 9726905
    },
    {
      "statusDate" : "2021-09-03",
      "vaccinationRate" : 54.98,
      "vaccinatedPersons" : 4753267,
      "administeredVaccineDoses" : 9759543
    },
    {
      "statusDate" : "2021-09-04",
      "vaccinationRate" : 55.05,
      "vaccinatedPersons" : 4759016,
      "administeredVaccineDoses" : 9776062
    },
    {
      "statusDate" : "2021-09-05",
      "vaccinationRate" : 55.06,
      "vaccinatedPersons" : 4759538,
      "administeredVaccineDoses" : 9778713
    },
    {
      "statusDate" : "2021-09-06",
      "vaccinationRate" : 55.16,
      "vaccinatedPersons" : 4768826,
      "administeredVaccineDoses" : 9802087
    },
    {
      "statusDate" : "2021-09-07",
      "vaccinationRate" : 55.29,
      "vaccinatedPersons" : 4779463,
      "administeredVaccineDoses" : 9827706
    },
    {
      "statusDate" : "2021-09-08",
      "vaccinationRate" : 55.43,
      "vaccinatedPersons" : 4792202,
      "administeredVaccineDoses" : 9860676
    },
    {
      "statusDate" : "2021-09-09",
      "vaccinationRate" : 55.57,
      "vaccinatedPersons" : 4804271,
      "administeredVaccineDoses" : 9894792
    },
    {
      "statusDate" : "2021-09-10",
      "vaccinationRate" : 55.77,
      "vaccinatedPersons" : 4821482,
      "administeredVaccineDoses" : 9938544
    },
    {
      "statusDate" : "2021-09-11",
      "vaccinationRate" : 55.87,
      "vaccinatedPersons" : 4830090,
      "administeredVaccineDoses" : 9965489
    },
    {
      "statusDate" : "2021-09-12",
      "vaccinationRate" : 55.88,
      "vaccinatedPersons" : 4831067,
      "administeredVaccineDoses" : 9969847
    },
    {
      "statusDate" : "2021-09-13",
      "vaccinationRate" : 56.02,
      "vaccinatedPersons" : 4842532,
      "administeredVaccineDoses" : 10002835
    },
    {
      "statusDate" : "2021-09-14",
      "vaccinationRate" : 56.17,
      "vaccinatedPersons" : 4855618,
      "administeredVaccineDoses" : 10038249
    },
    {
      "statusDate" : "2021-09-15",
      "vaccinationRate" : 56.36,
      "vaccinatedPersons" : 4871835,
      "administeredVaccineDoses" : 10079767
    },
    {
      "statusDate" : "2021-09-16",
      "vaccinationRate" : 56.54,
      "vaccinatedPersons" : 4887650,
      "administeredVaccineDoses" : 10117949
    },
    {
      "statusDate" : "2021-09-17",
      "vaccinationRate" : 56.77,
      "vaccinatedPersons" : 4907421,
      "administeredVaccineDoses" : 10162046
    },
    {
      "statusDate" : "2021-09-18",
      "vaccinationRate" : 56.89,
      "vaccinatedPersons" : 4917627,
      "administeredVaccineDoses" : 10185958
    },
    {
      "statusDate" : "2021-09-19",
      "vaccinationRate" : 56.89,
      "vaccinatedPersons" : 4918413,
      "administeredVaccineDoses" : 10189473
    },
    {
      "statusDate" : "2021-09-20",
      "vaccinationRate" : 57.04,
      "vaccinatedPersons" : 4930867,
      "administeredVaccineDoses" : 10218079
    },
    {
      "statusDate" : "2021-09-21",
      "vaccinationRate" : 57.20,
      "vaccinatedPersons" : 4944935,
      "administeredVaccineDoses" : 10250209
    },
    {
      "statusDate" : "2021-09-22",
      "vaccinationRate" : 57.39,
      "vaccinatedPersons" : 4960916,
      "administeredVaccineDoses" : 10284451
    },
    {
      "statusDate" : "2021-09-23",
      "vaccinationRate" : 57.59,
      "vaccinatedPersons" : 4978318,
      "administeredVaccineDoses" : 10319032
    },
    {
      "statusDate" : "2021-09-24",
      "vaccinationRate" : 57.83,
      "vaccinatedPersons" : 4999577,
      "administeredVaccineDoses" : 10356656
    },
    {
      "statusDate" : "2021-09-25",
      "vaccinationRate" : 57.98,
      "vaccinatedPersons" : 5012469,
      "administeredVaccineDoses" : 10379419
    },
    {
      "statusDate" : "2021-09-26",
      "vaccinationRate" : 58.00,
      "vaccinatedPersons" : 5013816,
      "administeredVaccineDoses" : 10382644
    },
    {
      "statusDate" : "2021-09-27",
      "vaccinationRate" : 58.18,
      "vaccinatedPersons" : 5029139,
      "administeredVaccineDoses" : 10409010
    },
    {
      "statusDate" : "2021-09-28",
      "vaccinationRate" : 58.33,
      "vaccinatedPersons" : 5042791,
      "administeredVaccineDoses" : 10434431
    },
    {
      "statusDate" : "2021-09-29",
      "vaccinationRate" : 58.54,
      "vaccinatedPersons" : 5060869,
      "administeredVaccineDoses" : 10464424
    },
    {
      "statusDate" : "2021-09-30",
      "vaccinationRate" : 58.74,
      "vaccinatedPersons" : 5078012,
      "administeredVaccineDoses" : 10491645
    },
    {
      "statusDate" : "2021-10-01",
      "vaccinationRate" : 58.98,
      "vaccinatedPersons" : 5098963,
      "administeredVaccineDoses" : 10523772
    },
    {
      "statusDate" : "2021-10-02",
      "vaccinationRate" : 59.11,
      "vaccinatedPersons" : 5110145,
      "administeredVaccineDoses" : 10541257
    },
    {
      "statusDate" : "2021-10-03",
      "vaccinationRate" : 59.14,
      "vaccinatedPersons" : 5112220,
      "administeredVaccineDoses" : 10544652
    },
    {
      "statusDate" : "2021-10-04",
      "vaccinationRate" : 59.33,
      "vaccinatedPersons" : 5129200,
      "administeredVaccineDoses" : 10569311
    }
  ]
}